flock_ui/.env.example
flock_ui/run.py
flock_ui/app/__init__.py
flock_ui/app/config.py
flock_ui/app/main.py
flock_ui/app/models_ui.py
flock_ui/app/api/__init__.py
flock_ui/app/api/agent_management.py
flock_ui/app/api/execution.py
flock_ui/app/api/flock_management.py
flock_ui/app/api/registry_viewer.py
flock_ui/app/services/__init__.py
flock_ui/app/services/flock_service.py
flock_ui/static/css/custom.css
flock_ui/templates/base.html
flock_ui/templates/flock_editor.html
flock_ui/templates/index.html
flock_ui/templates/registry_viewer.html
flock_ui/templates/partials/_agent_detail_form.html
flock_ui/templates/partials/_agent_list.html
flock_ui/templates/partials/_agent_manager_view.html
flock_ui/templates/partials/_agent_tools_checklist.html
flock_ui/templates/partials/_create_flock_form.html
flock_ui/templates/partials/_dashboard_flock_detail.html
flock_ui/templates/partials/_dashboard_flock_file_list.html
flock_ui/templates/partials/_dashboard_flock_properties_preview.html
flock_ui/templates/partials/_dashboard_upload_flock_form.html
flock_ui/templates/partials/_dynamic_input_form_content.html
flock_ui/templates/partials/_execution_form.html
flock_ui/templates/partials/_execution_view_container.html
flock_ui/templates/partials/_flock_file_list.html
flock_ui/templates/partials/_flock_properties_form.html
flock_ui/templates/partials/_flock_upload_form.html
flock_ui/templates/partials/_load_manage_view.html
flock_ui/templates/partials/_registry_table.html
flock_ui/templates/partials/_registry_viewer_content.html
flock_ui/templates/partials/_results_display.html
flock_ui/templates/partials/_sidebar.html
flock_ui/templates/partials/_structured_data_view.html
flock_ui-0.1.1.dist-info/METADATA
flock_ui-0.1.1.dist-info/WHEEL
flock_ui-0.1.1.dist-info/entry_points.txt
flock_ui-0.1.1.dist-info/RECORD
