Metadata-Version: 2.4
Name: flock-ui
Version: 0.1.1
Summary: Add your description here
Author-email: Andre Ratzenberger <andre.ratzenberger@whiteduck.de>
Requires-Python: >=3.10
Requires-Dist: fastapi>=0.115.12
Requires-Dist: flock-core[all]>=0.4.0b34
Requires-Dist: jinja2>=3.1.6
Requires-Dist: python-multipart>=0.0.20
Requires-Dist: uvicorn[standard]>=0.34.2
